sjts.pyd
shooju_ts-0.1.13.dist-info/DESCRIPTION.rst
shooju_ts-0.1.13.dist-info/METADATA
shooju_ts-0.1.13.dist-info/RECORD
shooju_ts-0.1.13.dist-info/WHEEL
shooju_ts-0.1.13.dist-info/metadata.json
shooju_ts-0.1.13.dist-info/top_level.txt
