Metadata-Version: 2.0
Name: shooju-ts
Version: 0.1.13
Summary: Shooju Time Series (SJTS) Serializer
Home-page: http://shooju.com
Author: Shooju, LLC
Author-email: support@shooju.com
License: TBD
Keywords: data,client,shooju
Platform: any
